LICENSE
MANIFEST.in
README.rst
setup.py
Plata.egg-info/PKG-INFO
Plata.egg-info/SOURCES.txt
Plata.egg-info/dependency_links.txt
Plata.egg-info/not-zip-safe
Plata.egg-info/top_level.txt
plata/__init__.py
plata/context_processors.py
plata/default_settings.py
plata/fields.py
plata/models.py
plata/utils.py
plata/contact/__init__.py
plata/contact/admin.py
plata/contact/forms.py
plata/contact/models.py
plata/contact/migrations/0001_initial.py
plata/contact/migrations/__init__.py
plata/discount/__init__.py
plata/discount/admin.py
plata/discount/models.py
plata/discount/migrations/0001_initial.py
plata/discount/migrations/0002_auto__del_field_discount_config_json__add_field_discount_config__del_f.py
plata/discount/migrations/__init__.py
plata/locale/de/LC_MESSAGES/django.mo
plata/locale/de/LC_MESSAGES/django.po
plata/payment/__init__.py
plata/payment/modules/__init__.py
plata/payment/modules/base.py
plata/payment/modules/cod.py
plata/payment/modules/paypal.py
plata/payment/modules/postfinance.py
plata/product/__init__.py
plata/product/models.py
plata/product/stock/__init__.py
plata/product/stock/admin.py
plata/product/stock/models.py
plata/reporting/__init__.py
plata/reporting/order.py
plata/reporting/product.py
plata/reporting/urls.py
plata/reporting/views.py
plata/shop/__init__.py
plata/shop/admin.py
plata/shop/forms.py
plata/shop/models.py
plata/shop/notifications.py
plata/shop/processors.py
plata/shop/signals.py
plata/shop/views.py
plata/shop/migrations/0001_initial.py
plata/shop/migrations/0002_auto__del_field_order_data_json__add_field_order_data__del_field_order.py
plata/shop/migrations/__init__.py
plata/shop/templates/_form_errors.html
plata/shop/templates/_form_item.html
plata/shop/templates/_form_item_plain.html
plata/shop/templates/_pagination.html
plata/shop/templates/base.html
plata/shop/templates/payment/paypal_form.html
plata/shop/templates/payment/postfinance_form.html
plata/shop/templates/plata/_address.html
plata/shop/templates/plata/_order_overview.html
plata/shop/templates/plata/shop_cart.html
plata/shop/templates/plata/shop_checkout.html
plata/shop/templates/plata/shop_confirmation.html
