Metadata-Version: 1.0
Name: Plata
Version: 1.0.0
Summary: Plata - the lean and mean Django-based Shop
Home-page: https://github.com/matthiask/plata/
Author: Matthias Kestenholz
Author-email: mk@feinheit.ch
License: BSD License
Platform: OS Independent
Classifier: Development Status :: 4 - Beta
Classifier: Environment :: Web Environment
Classifier: Framework :: Django
Classifier: Intended Audience :: Developers
Classifier: License :: OSI Approved :: BSD License
Classifier: Operating System :: OS Independent
Classifier: Programming Language :: Python
Classifier: Topic :: Internet :: WWW/HTTP :: Dynamic Content
Classifier: Topic :: Software Development
Classifier: Topic :: Software Development :: Libraries :: Application Frameworks
